{
  "date": "2026-04-13",
  "category": "general",
  "articles": [
    {
      "title": "米、イラン港湾の海上封鎖を日本時間13日午後11時から開始 イランは「海賊行為」と強く反発",
      "summary": "トランプ米政権はイランの港湾への出入りを封鎖する海上作戦を日本時間13日午後11時から開始すると発表した。イランは「違法であり海賊行為に等しい」と強く反発しており、軍事的緊張の一段の高まりが懸念されている。",
      "url": "https://news.web.nhk/newsweb/na/na-k10015097851000",
      "collectedAt": "2026-04-13T08:00:00+09:00"
    },
    {
      "title": "長期金利が一時2.49％に上昇、1999年以来の高水準 中東情勢の緊迫が影響",
      "summary": "日本の10年国債利回りが一時2.49％まで上昇し、1999年2月以来の高水準となった。米国によるホルムズ海峡封鎖表明を受けたインフレ懸念と原油高が債券売りを誘発し、金融政策の正常化観測と相まって長期金利を押し上げている。",
      "url": "https://www.nikkei.com/news/category/",
      "collectedAt": "2026-04-13T08:00:00+09:00"
    },
    {
      "title": "NY原油WTI、1バレル=105ドル台に急伸 供給不安で資源価格が上昇",
      "summary": "NY原油のWTI先物が一時1バレル=105ドル台に乗せた。ホルムズ海峡封鎖による供給途絶懸念が強まり、アジアのLNG価格にも波及する兆しが出ており、エネルギーコスト上昇による経済への影響が警戒されている。",
      "url": "https://www.nikkei.com/news/category/international/",
      "collectedAt": "2026-04-13T08:00:00+09:00"
    },
    {
      "title": "ハンガリー総選挙、オルバン首相率いる与党が大敗し政権交代へ",
      "summary": "ハンガリーで実施された総選挙でオルバン首相が率いる与党が大敗し、政権交代が確実となった。長期政権に対する国民の不満が噴出した形で、EU内でのハンガリーの外交スタンスにも影響を及ぼすとみられる。",
      "url": "https://sputniknews.jp/20260413/22504339.html",
      "collectedAt": "2026-04-13T08:00:00+09:00"
    },
    {
      "title": "台風4号が今年初の「強い」勢力に発達 13日以降マリアナ諸島付近を進む見込み",
      "summary": "台風4号が今年初めて「強い」勢力にまで発達した。13日から16日頃にかけてマリアナ諸島付近を進む見通しで、今後の進路次第では日本列島への影響も懸念され、気象庁が警戒を呼びかけている。",
      "url": "https://tenki.jp/forecaster/domoto_yukiyo/2026/04/11/38506.html",
      "collectedAt": "2026-04-13T08:00:00+09:00"
    }
  ]
}
